acquifer_napari_plugin/__init__.py
acquifer_napari_plugin/_reader.py
acquifer_napari_plugin/napari.yaml
acquifer_napari_plugin/utils.py
acquifer_napari_plugin/_tests/__init__.py
acquifer_napari_plugin/_tests/test_reader.py
acquifer_napari-0.0.2.dist-info/LICENSE
acquifer_napari-0.0.2.dist-info/METADATA
acquifer_napari-0.0.2.dist-info/WHEEL
acquifer_napari-0.0.2.dist-info/entry_points.txt
acquifer_napari-0.0.2.dist-info/top_level.txt
acquifer_napari-0.0.2.dist-info/RECORD
