Metadata-Version: 2.1
Name: acquifer-napari
Version: 0.0.2
Summary: Loader plugin for napari, to load Acquifer Imaging Machine datasets in napari, using dask for efficient lazy data-loading.
Author: Laurent Thomas
License: GPL-3.0-only
Project-URL: HomePage, https://acquifer.de
Project-URL: Twitter, https://twitter.com/myacquifer
Project-URL: Bug Tracker, https://github.com/Luxendo/acquifer-napari/issues
Project-URL: Documentation, https://github.com/Luxendo/acquifer-napari#README.md
Project-URL: Source Code, https://github.com/Luxendo/acquifer-napari
Classifier: Framework :: napari
Classifier: Topic :: Software Development :: Testing
Classifier: Programming Language :: Python
Classifier: Programming Language :: Python :: 3
Classifier: Programming Language :: Python :: 3.7
Classifier: Programming Language :: Python :: 3.8
Classifier: Programming Language :: Python :: 3.9
Classifier: Operating System :: OS Independent
Classifier: License :: OSI Approved :: GNU General Public License v3 (GPLv3)
Requires-Python: >=3.7
License-File: LICENSE
Requires-Dist: acquifer
Requires-Dist: napari
Requires-Dist: numpy
Requires-Dist: sortedcontainers
Requires-Dist: dask-image
Requires-Dist: xarray
